madr/__init__.py
madr/cli.py
madr/commands/__init__.py
madr/commands/init/__init__.py
madr/commands/init/command.py
madr/commands/init/template/.madr-config.yaml
madr/commands/init/template/README.md
madr/commands/init/template/docs/.empty
madr/commands/init/template/template/MADR.md
madr/commands/init/template/template/assets/.empty
madr-0.0.2.dist-info/entry_points.txt
madr-0.0.2.dist-info/WHEEL
madr-0.0.2.dist-info/METADATA
madr-0.0.2.dist-info/RECORD
