Metadata-Version: 2.1
Name: madr
Version: 0.0.2
Summary: A comprehensive toolset around making and managing MADRs using source control
Author: WilliamJohns
Author-email: will@wcj.dev
Requires-Python: >=3.7,<4.0
Classifier: Programming Language :: Python :: 3
Classifier: Programming Language :: Python :: 3.7
Classifier: Programming Language :: Python :: 3.8
Classifier: Programming Language :: Python :: 3.9
